Metadata-Version: 1.1
Name: QuakeCL
Version: 0.2.1
Summary: A command line tool that displays the recent earthquakes and aftershocks in Nepal.
Home-page: https://github.com/amitness/QuakeCL
Author: Amit Chaudhary
Author-email: meamitkc@gmail.com
License: MIT
Download-URL: https://github.com/amitness/QuakeCL/tarball/0.2.1
Platform: UNKNOWN
Classifier: Environment :: Console
Classifier: Programming Language :: Python :: 3
